paysync/__init__.py
paysync/paysync.py
paysync-0.1.0.dist-info/METADATA
paysync-0.1.0.dist-info/WHEEL
paysync-0.1.0.dist-info/top_level.txt
paysync-0.1.0.dist-info/RECORD
